colab_zirc_dims/__init__.py
colab_zirc_dims/gen_filename_fxns.py
colab_zirc_dims/alc_notebook_fxns/__init__.py
colab_zirc_dims/alc_notebook_fxns/alc_notebook_fxns.py
colab_zirc_dims/czd_utils/__init__.py
colab_zirc_dims/czd_utils/czd_utils.py
colab_zirc_dims/czd_utils/gen_czd_utils.py
colab_zirc_dims/eta/__init__.py
colab_zirc_dims/eta/eta.py
colab_zirc_dims/expl_vis/__init__.py
colab_zirc_dims/expl_vis/exp_plot_fxns.py
colab_zirc_dims/expl_vis/expl_vis.py
colab_zirc_dims/gen_notebook_fxns/__init__.py
colab_zirc_dims/gen_notebook_fxns/gen_notebook_fxns.py
colab_zirc_dims/jupyter_colab_compat/__init__.py
colab_zirc_dims/jupyter_colab_compat/output_local/__init__.py
colab_zirc_dims/jupyter_colab_compat/output_local/output_local.py
colab_zirc_dims/jupyter_colab_compat/patches/__init__.py
colab_zirc_dims/measure_utils/__init__.py
colab_zirc_dims/measure_utils/measure_utils.py
colab_zirc_dims/mos_match/__init__.py
colab_zirc_dims/mos_match/mos_match.py
colab_zirc_dims/mos_proc/__init__.py
colab_zirc_dims/mos_proc/mos_proc.py
colab_zirc_dims/non_std_cfgs/__init__.py
colab_zirc_dims/non_std_cfgs/non_std_cfgs.py
colab_zirc_dims/pointgen/__init__.py
colab_zirc_dims/pointgen/pointgen.py
colab_zirc_dims/poly_utils/__init__.py
colab_zirc_dims/poly_utils/poly_utils.py
colab_zirc_dims/save_load/__init__.py
colab_zirc_dims/save_load/save_load.py
colab_zirc_dims/segment/__init__.py
colab_zirc_dims/segment/segment.py
colab_zirc_dims/zirc_dims_GUI/__init__.py
colab_zirc_dims/zirc_dims_GUI/gen_zirc_dims_GUI.py
colab_zirc_dims/zirc_dims_GUI/gui_js.py
colab_zirc_dims/zirc_dims_GUI/zirc_dims_GUI.py
colab_zirc_dims-1.0.12.dist-info/licenses/LICENSE
colab_zirc_dims-1.0.12.dist-info/METADATA
colab_zirc_dims-1.0.12.dist-info/WHEEL
colab_zirc_dims-1.0.12.dist-info/top_level.txt
colab_zirc_dims-1.0.12.dist-info/RECORD
