Metadata-Version: 2.4
Name: colab_zirc_dims
Version: 1.0.12
Summary: Code to measure the dimensions of zircons from LA-ICP-MS alignment images in Google Colab, w/ deep learning automation.
Home-page: https://github.com/MCSitar/colab_zirc_dims
Author: Michael Cole Sitar
Author-email: clsitar5@gmail.com
License: Apache-2.0
Classifier: Programming Language :: Python :: 3
Classifier: License :: OSI Approved :: Apache Software License
Classifier: Operating System :: OS Independent
Requires-Python: >=3.7
License-File: LICENSE
Requires-Dist: ipython
Requires-Dist: matplotlib
Requires-Dist: numpy
Requires-Dist: pandas
Requires-Dist: Pillow
Requires-Dist: protobuf
Requires-Dist: scikit_image
Requires-Dist: opencv-python
Requires-Dist: joblib
Dynamic: license-file
